[
    {
        "name": "天津市救助管理站",
        "phone": "022-24126049",
        "address": "总站：天津市河东区小张贵庄路唐口新村南里"
    },
    {
        "name": "天津市救助管理站",
        "phone": "022-23972847",
        "address": "分站：天津市西青区大寺镇芦北口村西"
    },
    {
        "name": "天津市西青区救助管理站",
        "phone": "022-27390128",
        "address": "天津市西青区柳口路39号"
    },
    {
        "name": "天津市西青区救助管理站",
        "phone": "15620065618",
        "address": "天津市西青区柳口路39号"
    },
    {
        "name": "天津市武清区救助管理站",
        "phone": "022-29334014",
        "address": "天津市武清区杨村镇育才南里育红巷7排南"
    },
    {
        "name": "天津市宝坻区救助管理站",
        "phone": "022-29242200",
        "address": "天津市宝坻区进京路71号"
    },
    {
        "name": "天津市宝坻区救助管理站",
        "phone": "13512202166",
        "address": "天津市宝坻区进京路71号"
    },
    {
        "name": "天津市滨海新区塘沽救助管理站",
        "phone": "022-66591967",
        "address": "天津市滨海新区塘沽津塘公路金田路599号"
    },
    {
        "name": "天津市滨海新区汉沽救助管理站",
        "phone": "022-67197745",
        "address": "天津市滨海新区汉沽牌坊东街旅店院内"
    },
    {
        "name": "天津市滨海新区大港救助管理站",
        "phone": "022-63109933",
        "address": "天津市滨海新区大港迎宾街振兴路东南（老年福利院内）"
    },
    {
        "name": "天津市蓟县救助管理站",
        "phone": "022-29038376",
        "address": "天津市蓟县府前街4号"
    },
    {
        "name": "天津市蓟县救助管理站",
        "phone": "022-29142206",
        "address": "天津市蓟县府前街4号"
    },
    {
        "name": "天津市宁河县救助管理站",
        "phone": "022-69593536",
        "address": "天津市宁河县曹庄子道北（宁河县养老服务中心院内）"
    },
    {
        "name": "天津市静海县救助管理站",
        "phone": "022-28918609",
        "address": "天津市静海县胜利南路增114号"
    }
]